haunts/__init__.py
haunts/actions.py
haunts/calendars.py
haunts/cli.py
haunts/credentials.py
haunts/download.py
haunts/ini.py
haunts/report.py
haunts/spreadsheet.py
haunts-0.8.0.dist-info/AUTHORS.rst
haunts-0.8.0.dist-info/LICENSE
haunts-0.8.0.dist-info/METADATA
haunts-0.8.0.dist-info/WHEEL
haunts-0.8.0.dist-info/entry_points.txt
haunts-0.8.0.dist-info/top_level.txt
haunts-0.8.0.dist-info/RECORD
