Metadata-Version: 2.1
Name: haunts
Version: 0.8.0
Summary: Fill and sync Google Calendars with events taken from a Google spreadsheet
Home-page: https://github.com/keul/haunts
Author: Luca Fabbri
Author-email: l.fabbri@bopen.eu
License: GNU General Public License v3
Keywords: google-calendar spreadsheet reports worklog
Classifier: Development Status :: 4 - Beta
Classifier: Intended Audience :: End Users/Desktop
Classifier: License :: OSI Approved :: GNU General Public License v3 (GPLv3)
Classifier: Natural Language :: English
Classifier: Programming Language :: Python :: 3
Classifier: Programming Language :: Python :: 3.10
Classifier: Programming Language :: Python :: 3.11
Requires-Python: >=3.9
License-File: LICENSE
License-File: AUTHORS.rst
Requires-Dist: setuptools
Requires-Dist: Click >=7.0
Requires-Dist: colorama
Requires-Dist: python-dateutil
Requires-Dist: google-api-python-client
Requires-Dist: google-auth-httplib2
Requires-Dist: google-auth-oauthlib
Requires-Dist: google-auth <2dev
Requires-Dist: tabulate
